odoo8_addon_crm_timesheet-8.0.1.0.0.99.dev8-py2.7-nspkg.pth
odoo8_addon_crm_timesheet-8.0.1.0.0.99.dev8.dist-info/METADATA
odoo8_addon_crm_timesheet-8.0.1.0.0.99.dev8.dist-info/RECORD
odoo8_addon_crm_timesheet-8.0.1.0.0.99.dev8.dist-info/WHEEL
odoo8_addon_crm_timesheet-8.0.1.0.0.99.dev8.dist-info/namespace_packages.txt
odoo8_addon_crm_timesheet-8.0.1.0.0.99.dev8.dist-info/top_level.txt
odoo_addons/crm_timesheet/README.rst
odoo_addons/crm_timesheet/__init__.py
odoo_addons/crm_timesheet/__openerp__.py
odoo_addons/crm_timesheet/i18n/crm_timesheet.pot
odoo_addons/crm_timesheet/i18n/es.po
odoo_addons/crm_timesheet/i18n/fr.po
odoo_addons/crm_timesheet/i18n/sl.po
odoo_addons/crm_timesheet/models/__init__.py
odoo_addons/crm_timesheet/models/crm_lead.py
odoo_addons/crm_timesheet/models/crm_phonecall.py
odoo_addons/crm_timesheet/models/hr_analytic_timesheet.py
odoo_addons/crm_timesheet/static/description/icon.png
odoo_addons/crm_timesheet/tests/__init__.py
odoo_addons/crm_timesheet/tests/base.py
odoo_addons/crm_timesheet/tests/test_crm_phonecall.py
odoo_addons/crm_timesheet/views/crm_lead_view.xml
odoo_addons/crm_timesheet/views/crm_phonecall_view.xml
odoo_addons/crm_timesheet/views/hr_analytic_timesheet_view.xml
