Metadata-Version: 2.1
Name: odoo8-addon-crm-timesheet
Version: 8.0.1.0.0.99.dev8
Summary: CRM Timesheet
Home-page: http://www.antiun.com
Author: Antiun Ingeniería S.L.,Odoo Community Association (OCA)
Author-email: support@odoo-community.org
License: AGPL-3
Platform: UNKNOWN
Classifier: Programming Language :: Python
Classifier: Framework :: Odoo
Classifier: License :: OSI Approved :: GNU Affero General Public License v3
Requires-Python: ~=2.7
Requires-Dist: odoo (<9.0a,>=8.0a)
